quicktimekeeper/__main__.py
quicktimekeeper/test_main.py
quicktimer/__main__.py
quicktimer/test_main.py
quicktimekeeper-1.0.0.dist-info/METADATA
quicktimekeeper-1.0.0.dist-info/WHEEL
quicktimekeeper-1.0.0.dist-info/entry_points.txt
quicktimekeeper-1.0.0.dist-info/top_level.txt
quicktimekeeper-1.0.0.dist-info/RECORD
