Metadata-Version: 2.1
Name: quicktimekeeper
Version: 1.0.0
Summary: Quickly time functions easily
Home-page: https://github.com/DarkWolf2244/QuickTimer
Author: DarkWolf
Author-email: darkwolfx2244@gmail.com
License: MIT
Platform: UNKNOWN
Classifier: License :: OSI Approved :: MIT License
Classifier: Programming Language :: Python :: 3
Classifier: Programming Language :: Python :: 3.7
